{"id":"B4gj","dependencies":[{"name":"C:\\Users\\User\\Documents\\D3\\01-homework\\homework\\package.json","includedInParent":true,"mtime":1537033862922}],"generated":{"js":"module.exports=\"/storytelling-first-homework/b21b522bdfec5426a5ae0c8773847ff1.csv\";","map":{"mappings":[{"source":"0","name":"module","original":{"line":1,"column":0},"generated":{"line":1,"column":0}},{"source":"0","name":"exports","original":{"line":1,"column":7},"generated":{"line":1,"column":7}},{"source":"0","original":{"line":1,"column":17},"generated":{"line":1,"column":15}}],"sources":{},"lineCount":null}},"hash":"6869bac724d3e5b598e372e4dfbf65b2","cacheData":{"env":{}}}